Workbook

Sheet READ ME
A1: BASE DE DONNÉES - TARIFICATION HVAC RÉGION MENA
A3: Objectif :
A4: Ce classeur sert de base de données pour calculer un prix estimé (devis) de réparation ou
A5: d'installation HVAC (climatisation, chauffage, ventilation) dans les pays de la région MENA.
A7: Formule de calcul du prix final :
A8: prix_final = coût_base(pièces, converti en devise locale, SANS multiplicateur)
A9: + (heures_estimées × taux_horaire_local × ajustement_régional × multiplicateur_urgence
A10: × multiplicateur_complexité × multiplicateur_saisonnier)
A11: + marge_fixe (convertie) + coût_appareil × facteur_importation (converti, = 0 si réparation)
A12: ⚠️ Logique IMPORTANTE pour éviter un prix exagéré :
A14: ⚠️ CORRECTION v3 (suite à audit) :
A15: Dans la v2, les multiplicateurs (urgence/complexité/saisonnier) étaient appliqués au COÛT DES PIÈCES en plus
... A66: main d'œuvre, fiscalité locale, variations de change).

Sheet Types_Pannes_Installations
A1: code | B1: categorie | C1: sous_categorie | D1: nom_intervention | E1: type_intervention | F1: cout_base_usd_pieces | G1: heures_estimees | H1: notes
A2: CLR001 | B2: Climatisation | C2: Réparation Split/Central/Fenêtre | D2: Climatiseur ne démarre pas - diagnostic électrique | E2: Reparation | F2: 26 | G2: 1
A3: CLR002 | B3: Climatisation | C3: Réparation Split/Central/Fenêtre | D3: Remplacement condensateur de démarrage (run capacitor) | E3: Reparation | F3: 53 | G3: 1
A4: CLR003 | B4: Climatisation | C4: Réparation Split/Central/Fenêtre | D4: Remplacement relais de démarrage (start relay) | E4: Reparation | F4: 44 | G4: 0.8
A5: CLR004 | B5: Climatisation | C5: Réparation Split/Central/Fenêtre | D5: Recharge gaz réfrigérant R410A (par kg) | E5: Reparation | F5: 64 | G5: 1.5
A6: CLR005 | B6: Climatisation | C6: Réparation Split/Central/Fenêtre | D6: Recharge gaz réfrigérant R22 (par kg, obsolète) | E6: Reparation | F6: 82 | G6: 1.5
A7: CLR006 | B7: Climatisation | C7: Réparation Split/Central/Fenêtre | D7: Réparation fuite de réfrigérant - localisation et soudure | E7: Reparation | F7: 94 | G7: 2.5
A8: CLR007 | B8: Climatisation | C8: Réparation Split/Central/Fenêtre | D8: Remplacement compresseur climatiseur split | E8: Reparation | F8: 100 | G8: 4 | H8: Recalibré (2026) - voir Lisez_moi / Verification_Exemples - Source: SM-Devis.tn
A9: CLR008 | B9: Climatisation | C9: Réparation Split/Central/Fenêtre | D9: Remplacement compresseur climatiseur central | E9: Reparation | F9: 424 | G9: 5.5
A10: CLR009 | B10: Climatisation | C10: Réparation Split/Central/Fenêtre | D10: Nettoyage évaporateur (unité intérieure) | E10: Reparation | F10: 32 | G10: 1
A11: CLR010 | B11: Climatisation | C11: Réparation Split/Central/Fenêtre | D11: Nettoyage condenseur (unité extérieure) | E11: Reparation | F11: 38 | G11: 1.2
A12: CLR011 | B12: Climatisation | C12: Réparation Split/Central/Fenêtre | D12: Remplacement filtre à air standard | E12: Reparation | F12: 10 | G12: 0.3
A13: CLR012 | B13: Climatisation | C13: Réparation Split/Central/Fenêtre | D13: Remplacement filtre HEPA / haute efficacité | E13: Reparation | F13: 22 | G13: 0.4
A14: CLR013 | B14: Climatisation | C14: Réparation Split/Central/Fenêtre | D14: Réparation ventilateur unité intérieure (moteur) | E14: Reparation | F14: 68 | G14: 1.5
A15: CLR014 | B15: Climatisation | C15: Réparation Split/Central/Fenêtre | D15: Remplacement moteur ventilateur extérieur | E15: Reparation | F15: 99 | G15: 2
A16: CLR015 | B16: Climatisation | C16: Réparation Split/Central/Fenêtre | D16: Réparation carte électronique (PCB) climatiseur | E16: Reparation | F16: 82 | G16: 1.5
A17: CLR016 | B17: Climatisation | C17: Réparation Split/Central/Fenêtre | D17: Remplacement carte électronique complète | E17: Reparation | F17: 123 | G17: 2
A18: CLR017 | B18: Climatisation | C18: Réparation Split/Central/Fenêtre | D18: Réparation télécommande / module de réception | E18: Reparation | F18: 26 | G18: 0.5
A19: CLR018 | B19: Climatisation | C19: Réparation Split/Central/Fenêtre | D19: Débouchage tuyau d'évacuation des condensats | E19: Reparation | F19: 28 | G19: 0.8
A20: CLR019 | B20: Climatisation | C20: Réparation Split/Central/Fenêtre | D20: Réparation pompe de relevage des condensats | E20: Reparation | F20: 53 | G20: 1.2
... A162: CTR161 | B162: Contrôles | C162: Thermostats/Domotique | D162: Mise à jour firmware système de contrôle | E162: Reparation | F162: 18 | G162: 0.5
A163: MNT162 | B163: Maintenance | C163: Entretien préventif | D163: Entretien annuel climatiseur split (standard) | E163: Reparation | F163: 8 | G163: 0.7 | H163: Recalibré (2026) - voir Lisez_moi / Verification_Exemples - Source: SM-Devis.tn
A164: MNT163 | B164: Maintenance | C164: Entretien préventif | D164: Entretien annuel climatiseur central | E164: Reparation | F164: 44 | G164: 1.8
A165: MNT164 | B165: Maintenance | C165: Entretien préventif | D165: Entretien annuel chaudière gaz (obligatoire) | E165: Reparation | F165: 32 | G165: 1.2
A166: MNT165 | B166: Maintenance | C166: Entretien préventif | D166: Entretien annuel pompe à chaleur | E166: Reparation | F166: 47 | G166: 1.5
A167: MNT166 | B167: Maintenance | C167: Entretien préventif | D167: Contrat de maintenance préventive (visite trimestrielle) | E167: Reparation | F167: 64 | G167: 2
A168: MNT167 | B168: Maintenance | C168: Entretien préventif | D168: Inspection pré-saison été (check-up complet) | E168: Reparation | F168: 26 | G168: 1
A169: MNT168 | B169: Maintenance | C169: Entretien préventif | D169: Inspection pré-saison hiver (check-up complet) | E169: Reparation | F169: 26 | G169: 1
A170: MNT169 | B170: Maintenance | C170: Entretien préventif | D170: Nettoyage et vérification générale système gainable | E170: Reparation | F170: 70 | G170: 2.5
A171: MNT170 | B171: Maintenance | C171: Entretien préventif | D171: Test de performance énergétique du système | E171: Reparation | F171: 47 | G171: 1.5
A172: MNT171 | B172: Maintenance | C172: Entretien préventif | D172: Audit énergétique complet installation HVAC | E172: Reparation | F172: 94 | G172: 3
A173: ELE172 | B173: Électrique | C173: Composants électriques | D173: Diagnostic électrique général panne HVAC | E173: Reparation | F173: 23 | G173: 0.8
A174: ELE173 | B174: Électrique | C174: Composants électriques | D174: Remplacement contacteur compresseur | E174: Reparation | F174: 47 | G174: 1.2
A175: ELE174 | B175: Électrique | C175: Composants électriques | D175: Réparation court-circuit câblage HVAC | E175: Reparation | F175: 53 | G175: 1.5
... A251: DIV250 | B251: Divers/Complémentaire | C251: Réparations et installations complémentaires | D251: Formation utilisateur sur nouveau système installé | E251: Installation | F251: 5 | G251: 0.55
A253: cout_base_usd_pieces = coût des pièces/fournitures uniquement (hors main d'œuvre, hors appareil neuf). La main d'œuvre est ajoutée via heures_estimees x taux_horaire_local (feuille Donnees_Regionales_MENA).

Sheet Multiplicateurs_Urgence
A1: niveau_urgence | B1: description | C1: delai_intervention | D1: multiplicateur_urgence
A2: Standard | B2: Intervention planifiée à l'avance | C2: 3 à 7 jours | D2: 1
A3: Rapide | B3: Intervention sous 24 à 48h | C3: 24-48 heures | D3: 1.1
A4: Urgent | B4: Intervention le jour même | C4: Même jour | D4: 1.2
A5: Urgence immédiate | B5: Intervention sous 2 heures (panne critique) | C5: < 2 heures | D5: 1.4
A6: Nuit / Week-end / Jour férié | B6: Intervention en dehors des heures ouvrées | C6: Variable | D6: 1.3

Sheet Multiplicateurs_Complexite
A1: niveau_complexite | B1: description | C1: multiplicateur_complexite
A2: Simple | B2: Intervention standard, accès facile, équipement courant | C2: 1
A3: Modérée | B3: Nécessite un diagnostic approfondi ou un accès partiellement difficile | C3: 1.1
A4: Élevée | B4: Système complexe (gainable, multi-split, commercial), accès difficile | C4: 1.25
A5: Très élevée | B5: Système industriel/commercial de grande capacité, hauteur, toiture, espace confiné | C5: 1.45
A6: Exceptionnelle | B6: Cas rare nécessitant équipement spécialisé ou intervention multi-techniciens | C6: 1.7

Sheet Multiplicateurs_Saisonnier
A1: periode | B1: mois_concernes | C1: description | D1: multiplicateur_saisonnier
A2: Haute saison été (clim) | B2: Juin - Septembre | C2: Forte demande climatisation, délais tendus | D2: 1.15
A3: Haute saison hiver (chauffage) | B3: Décembre - Février | C3: Forte demande chauffage | D3: 1.08
A4: Saison intermédiaire | B4: Mars - Mai | C4: Demande modérée | D4: 1
A5: Basse saison | B5: Octobre - Novembre | C5: Faible demande, disponibilité technicien élevée | D5: 0.92
A6: Période de canicule / vague de chaleur | B6: Variable (pic été) | C6: Pic exceptionnel de demande | D6: 1.25

Sheet Donnees_Regionales_MENA
A1: pays | B1: devise | C1: code_devise | D1: taux_change_vers_USD_1USD_equiv | E1: taux_horaire_local_technicien | F1: ajustement_regional_main_oeuvre | G1: facteur_importation_appareil | H1: source_indicative
A2: Tunisie | B2: Dinar tunisien | C2: TND | D2: 3.1 | E2: 35 | F2: 1 | G2: 1.1 | H2: ProTunisie/ClimChaud/SM-Devis 2025 (référence calibration)
A3: Maroc | B3: Dirham marocain | C3: MAD | D3: 9.95 | E3: 110 | F3: 1.05 | G3: 1.1 | H3: ComptoirElectro.ma/Mano.ma 2025-26
A4: Algérie | B4: Dinar algérien | C4: DZD | D4: 134 | E4: 850 | F4: 0.9 | G4: 1.15 | H4: Estimation marché formel/informel Algérie 2025
A5: Égypte | B5: Livre égyptienne | C5: EGP | D5: 49.5 | E5: 200 | F5: 0.88 | G5: 1.2 | H5: Estimation marché Caire/Alexandrie 2025
A6: Libye | B6: Dinar libyen | C6: LYD | D6: 4.85 | E6: 33 | F6: 0.9 | G6: 1.15 | H6: Estimation marché Tripoli 2025
A7: Arabie Saoudite | B7: Riyal saoudien | C7: SAR | D7: 3.75 | E7: 65 | F7: 1.15 | G7: 1.05 | H7: Estimation marché Riyad/Jeddah 2025
A8: Émirats Arabes Unis | B8: Dirham émirati | C8: AED | D8: 3.67 | E8: 75 | F8: 1.2 | G8: 1.05 | H8: Estimation marché Dubaï/Abu Dhabi 2025
A9: Qatar | B9: Riyal qatari | C9: QAR | D9: 3.64 | E9: 78 | F9: 1.2 | G9: 1.05 | H9: Estimation marché Doha 2025
A10: Koweït | B10: Dinar koweïtien | C10: KWD | D10: 0.31 | E10: 7.5 | F10: 1.18 | G10: 1.05 | H10: Estimation marché Koweït City 2025
A11: Bahreïn | B11: Dinar bahreïni | C11: BHD | D11: 0.377 | E11: 8 | F11: 1.12 | G11: 1.05 | H11: Estimation marché Manama 2025
A12: Oman | B12: Riyal omanais | C12: OMR | D12: 0.385 | E12: 7.5 | F12: 1.1 | G12: 1.05 | H12: Estimation marché Mascate 2025
A13: Jordanie | B13: Dinar jordanien | C13: JOD | D13: 0.709 | E13: 6.5 | F13: 1 | G13: 1.1 | H13: Estimation marché Amman 2025
... A15: Irak | B15: Dinar irakien | C15: IQD | D15: 1310 | E15: 8500 | F15: 0.92 | G15: 1.2 | H15: Estimation marché Bagdad/Erbil 2025
A17: Notes :
A18: - taux_change_vers_USD : nombre d'unités de devise locale pour 1 USD (ordre de grandeur, à actualiser).
A19: - taux_horaire_local_technicien : tarif horaire moyen d'un technicien HVAC qualifié, EN DEVISE LOCALE.
A20: C'est ICI que la différence de coût de main d'œuvre entre pays MENA est prise en compte (et non sur
A21: le coût des pièces, qui reste proche d'un prix d'importation international car le matériel HVAC est
A22: majoritairement importé partout dans la région).
A23: - ajustement_regional_main_oeuvre : facteur modéré (0.85 à 1.20) appliqué UNIQUEMENT à la composante
A24: main d'œuvre (heures_estimees x taux_horaire_local, déjà en devise locale). Il reflète des écarts de
A25: positionnement de marché (formel/informel, zone urbaine/rurale), pas un facteur de conversion de devise.
A26: - facteur_importation_appareil : majoration appliquée au coût des appareils neufs importés (droits de
A27: douane, transport, marge distributeur), appliquée uniquement sur la feuille Cout_Appareil.

Sheet Marge_Fixe
A1: type_intervention | B1: marge_fixe_usd | C1: description
A2: Reparation | B2: 3 | C2: Marge fixe couvrant déplacement et frais administratifs (réparations) - montant volontairement modeste
A3: Installation | B3: 6 | C3: Marge fixe couvrant déplacement, mise en service et suivi (installations) - montant volontairement modeste
A5: Note | C5: La marge_fixe est exprimée en USD ; elle doit être convertie en devise locale avec le même
C6: taux_change_vers_USD que la composante coût_base avant d'être additionnée au prix final.

Sheet Cout_Appareil
A1: categorie_appareil | B1: modele_type | C1: puissance_capacite | D1: cout_appareil_usd_moyen | E1: notes
A2: Climatiseur split mural | B2: Entrée de gamme | C2: 9000 BTU | D2: 230 | E2: Marque locale/générique (ex. Condor, Saba)
A3: Climatiseur split mural | B3: Milieu de gamme | C3: 12000 BTU | D3: 310 | E3: Marque reconnue (Midea, Gree, TCL)
A4: Climatiseur split mural | B4: Milieu de gamme | C4: 18000 BTU | D4: 420 | E4: Marque reconnue
A5: Climatiseur split mural | B5: Haut de gamme inverter | C5: 12000 BTU | D5: 480 | E5: Daikin, Mitsubishi, Samsung, LG
A6: Climatiseur split mural | B6: Haut de gamme inverter | C6: 18000 BTU | D6: 650 | E6: Daikin, Mitsubishi, Samsung, LG
A7: Climatiseur gainable | B7: Résidentiel standard | C7: 24000-36000 BTU | D7: 1800 | E7: Unité + air handler
A8: Climatiseur central | B8: Résidentiel | C8: 3 tonnes | D8: 2300 | E8: Groupe extérieur + air handler
A9: Climatiseur cassette | B9: Commercial léger | C9: 24000 BTU | D9: 800 | E9: Cassette plafonnière 4 voies
A10: Climatiseur fenêtre | B10: Standard | C10: 9000-12000 BTU | D10: 180
A11: Climatiseur portable | B11: Standard | C11: 9000-12000 BTU | D11: 230
A12: Chaudière gaz murale | B12: Standard non condensation | C12: 24 kW | D12: 700
A13: Chaudière gaz murale | B13: Condensation haute efficacité | C13: 24 kW | D13: 1200
A14: Chaudière fioul | B14: Standard | C14: 30 kW | D14: 1350
A15: Pompe à chaleur air-air | B15: Résidentiel | C15: 12000 BTU | D15: 800
A16: Pompe à chaleur air-eau | B16: Résidentiel | C16: 8-12 kW | D16: 3600
A17: Pompe à chaleur géothermique | B17: Résidentiel | C17: 10 kW | D17: 6500
A18: Fournaise au gaz | B18: Résidentielle | C18: 80 000-100 000 BTU | D18: 1200
A19: Fournaise électrique | B19: Résidentielle | C19: 15 kW | D19: 800
A20: Chauffe-eau électrique | B20: Standard | C20: 50 L | D20: 100
A21: Chauffe-eau électrique | B21: Standard | C21: 100 L | D21: 160
... A25: VMC double flux | B25: Résidentielle | C25: avec échangeur | D25: 800
A26: Thermostat connecté | B26: Smart | C26: - | D26: 90 | E26: Nest, Ecobee, ou équivalent local
A27: Thermostat programmable | B27: Basique | C27: - | D27: 35
A28: Humidificateur central | B28: Résidentiel | C28: standard | D28: 230
A29: Déshumidificateur central | B29: Résidentiel | C29: standard | D29: 270
A30: Purificateur d'air centralisé | B30: Résidentiel | C30: avec filtre HEPA | D30: 320
A31: Rooftop unit commercial | B31: Standard | C31: 5 tonnes | D31: 5000
A32: Chiller industriel | B32: Petite capacité | C32: 20-30 tonnes | D32: 10500
A33: Centrale de traitement d'air (CTA) | B33: Commercial | C33: standard | D33: 5500
A34: Poêle à granulés | B34: Résidentiel | C34: 8 kW | D34: 1200
A35: Insert de cheminée | B35: Résidentiel | C35: standard | D35: 900
A37: Note : prix appareil seul (hors pose), avant application du facteur_importation_appareil par pays (feuille Donnees_Regionales_MENA).

Sheet Exemple_Calcul
A1: CALCULATEUR DE PRIX - EXEMPLE D'APPLICATION DE LA FORMULE
A3: Formule :
A4: prix_final = (coût_base_pièces convertie en devise locale)
A5: + (heures_estimées × taux_horaire_local × ajustement_régional × mult_urgence × mult_complexité × mult_saisonnier)
A6: + marge_fixe (convertie) + coût_appareil × facteur_importation (converti, = 0 si réparation)
A8: PARAMÈTRES D'ENTRÉE (à modifier pour simuler un devis)
A9: Code intervention (voir feuille Types_Pannes_Installations) | C9: CLR007
A10: Pays (voir feuille Donnees_Regionales_MENA) | C10: Tunisie
A11: Niveau d'urgence (voir feuille Multiplicateurs_Urgence) | C11: Urgent
A12: Niveau de complexité (voir feuille Multiplicateurs_Complexite) | C12: Modérée
A13: Période / saison (voir feuille Multiplicateurs_Saisonnier) | C13: Haute saison été (clim)
A14: Appareil neuf requis ? (OUI/NON) | C14: NON
A15: Catégorie appareil (si OUI, voir feuille Cout_Appareil) | C15: Climatiseur split mural
A17: VALEURS RÉCUPÉRÉES
A18: nom_intervention | C18: =IFERROR(VLOOKUP($C$9,Types_Pannes_Installations!A:H,4,FALSE()),"Code introuvable") -> Remplacement compresseur climatiseur split
A19: type_intervention | C19: =IFERROR(VLOOKUP($C$9,Types_Pannes_Installations!A:H,5,FALSE()),"") -> Reparation
A20: cout_base_usd_pieces | C20: =IFERROR(VLOOKUP($C$9,Types_Pannes_Installations!A:H,6,FALSE()),0) -> 100
A21: heures_estimees | C21: =IFERROR(VLOOKUP($C$9,Types_Pannes_Installations!A:H,7,FALSE()),0) -> 4
A22: multiplicateur_urgence | C22: =IFERROR(VLOOKUP($C$11,Multiplicateurs_Urgence!A:D,4,FALSE()),1) -> 1.2
A23: multiplicateur_complexite | C23: =IFERROR(VLOOKUP($C$12,Multiplicateurs_Complexite!A:C,3,FALSE()),1) -> 1.1
A24: multiplicateur_saisonnier | C24: =IFERROR(VLOOKUP($C$13,Multiplicateurs_Saisonnier!A:D,4,FALSE()),1) -> 1.15
A25: devise_pays | C25: =IFERROR(VLOOKUP($C$10,Donnees_Regionales_MENA!A:H,2,FALSE()),"") -> Dinar tunisien
A26: taux_change_vers_USD | C26: =IFERROR(VLOOKUP($C$10,Donnees_Regionales_MENA!A:H,4,FALSE()),1) -> 3.1
A27: taux_horaire_local | C27: =IFERROR(VLOOKUP($C$10,Donnees_Regionales_MENA!A:H,5,FALSE()),0) -> 35
A28: ajustement_regional_main_oeuvre | C28: =IFERROR(VLOOKUP($C$10,Donnees_Regionales_MENA!A:H,6,FALSE()),1) -> 1
A29: facteur_importation_appareil | C29: =IFERROR(VLOOKUP($C$10,Donnees_Regionales_MENA!A:H,7,FALSE()),1) -> 1.1
A30: marge_fixe_usd | C30: =IFERROR(VLOOKUP($C$19,Marge_Fixe!A:C,2,FALSE()),0) -> 3
A31: cout_appareil_usd | C31: =IF($C$14="OUI",IFERROR(AVERAGEIF(Cout_Appareil!A:D,$C$15,Cout_Appareil!D:D),0),0) -> 0
A32: DÉTAIL DU CALCUL
A33: 1) Coût pièces converti en devise locale (PAS de multiplicateur ici) | C33: =$C$20*$C$26 -> 310
A34: 2) (supprimé - fusionné avec ligne 1)
A35: 3) Main d'œuvre locale ajustée x multiplicateurs (devise locale) | C35: =$C$21*$C$27*$C$28*$C$22*$C$23*$C$24 -> 212.52
A36: 4) Marge fixe convertie en devise locale | C36: =$C$30*$C$26 -> 9.3
A37: 5) Coût appareil neuf (avec import) converti en devise locale | C37: =$C$31*$C$29*$C$26 -> 0
A39: PRIX FINAL ESTIMÉ (devise locale) | C39: =$C$33+$C$35+$C$36+$C$37 -> 531.82 | D39: =$C$25 -> Dinar tunisien
A40: Équivalent approximatif en USD | C40: =$C$39/$C$26 -> 171.55484
A42: Astuce : changez les valeurs bleues (paramètres d'entrée) ci-dessus pour simuler n'importe quel devis.
A43: Vérification (Tunisie, code CLR007 compresseur split) : voir feuille Verification_Exemples pour le détail Tunisie + Maroc comparé aux prix marché réels.

Sheet Verification_Exemples
A1: VÉRIFICATION - COMPARAISON PRIX CALCULÉS vs PRIX MARCHÉ RÉELS (Tunisie & Maroc)
A2: Objectif : valider que la formule recalibrée (multiplicateurs appliqués UNIQUEMENT à la main d'œuvre, pas aux pièces) donne des prix réalistes, comparés aux fourchettes trouvées en ligne (sources citées).
A4: Pays | B4: Code | C4: Intervention | D4: Urgence | E4: Complexité | F4: Saison | G4: cout_base_usd | H4: heures | I4: taux_change | J4: taux_horaire_local | K4: ajustement_regional | L4: mult_urgence | M4: mult_complexite | N4: mult_saisonnier | O4: marge_fixe_usd | P4: Prix_pieces_local | Q4: Prix_MO_local | R4: Marge_local | S4: PRIX_FINAL_local | T4: devise | U4: Equivalent_USD | V4: Fourchette_marche_reelle | W4: Source
A5: Tunisie | B5: CLR007 | C5: =IFERROR(VLOOKUP($B5,Types_Pannes_Installations!A:H,4,FALSE()),"?") -> Remplacement compresseur climatiseur split | D5: Standard | E5: Simple | F5: Saison intermédiaire | G5: =IFERROR(VLOOKUP($B5,Types_Pannes_Installations!A:H,6,FALSE()),0) -> 100 | H5: =IFERROR(VLOOKUP($B5,Types_Pannes_Installations!A:H,7,FALSE()),0) -> 4 | I5: =IFERROR(VLOOKUP($A5,Donnees_Regionales_MENA!A:H,4,FALSE()),1) -> 3.1 | J5: =IFERROR(VLOOKUP($A5,Donnees_Regionales_MENA!A:H,5,FALSE()),0) -> 35 | K5: =IFERROR(VLOOKUP($A5,Donnees_Regionales_MENA!A:H,6,FALSE()),1) -> 1 | L5: =IFERROR(VLOOKUP($D5,Multiplicateurs_Urgence!A:D,4,FALSE()),1) -> 1 | M5: =IFERROR(VLOOKUP($E5,Multiplicateurs_Complexite!A:C,3,FALSE()),1) -> 1 | N5: =IFERROR(VLOOKUP($F5,Multiplicateurs_Saisonnier!A:D,4,FALSE()),1) -> 1 | O5: =IFERROR(VLOOKUP(VLOOKUP($B5,Types_Pannes_Installations!A:H,5,FALSE()),Marge_Fixe!A:C,2,FALSE()),0) -> 3 | P5: =$G5*$I5 -> 310 | Q5: =$H5*$J5*$K5*$L5*$M5*$N5 -> 140 | R5: =$O5*$I5 -> 9.3 | S5: =$P5+$Q5+$R5 -> 459.3 | T5: =IFERROR(VLOOKUP($A5,Donnees_Regionales_MENA!A:H,2,FALSE()),"") -> Dinar tunisien | U5: =$S5/$I5 -> 148.16129 | V5: 300 - 700 DT (pièce 150-450 DT + main d'œuvre) | W5: SM-Devis.tn 2025
A6: Tunisie | B6: CLR007 | C6: =IFERROR(VLOOKUP($B6,Types_Pannes_Installations!A:H,4,FALSE()),"?") -> Remplacement compresseur climatiseur split | D6: Urgent | E6: Modérée | F6: Haute saison été (clim) | G6: =IFERROR(VLOOKUP($B6,Types_Pannes_Installations!A:H,6,FALSE()),0) -> 100 | H6: =IFERROR(VLOOKUP($B6,Types_Pannes_Installations!A:H,7,FALSE()),0) -> 4 | I6: =IFERROR(VLOOKUP($A6,Donnees_Regionales_MENA!A:H,4,FALSE()),1) -> 3.1 | J6: =IFERROR(VLOOKUP($A6,Donnees_Regionales_MENA!A:H,5,FALSE()),0) -> 35 | K6: =IFERROR(VLOOKUP($A6,Donnees_Regionales_MENA!A:H,6,FALSE()),1) -> 1 | L6: =IFERROR(VLOOKUP($D6,Multiplicateurs_Urgence!A:D,4,FALSE()),1) -> 1.2 | M6: =IFERROR(VLOOKUP($E6,Multiplicateurs_Complexite!A:C,3,FALSE()),1) -> 1.1 | N6: =IFERROR(VLOOKUP($F6,Multiplicateurs_Saisonnier!A:D,4,FALSE()),1) -> 1.15 | O6: =IFERROR(VLOOKUP(VLOOKUP($B6,Types_Pannes_Installations!A:H,5,FALSE()),Marge_Fixe!A:C,2,FALSE()),0) -> 3 | P6: =$G6*$I6 -> 310 | Q6: =$H6*$J6*$K6*$L6*$M6*$N6 -> 212.52 | R6: =$O6*$I6 -> 9.3 | S6: =$P6+$Q6+$R6 -> 531.82 | T6: =IFERROR(VLOOKUP($A6,Donnees_Regionales_MENA!A:H,2,FALSE()),"") -> Dinar tunisien | U6: =$S6/$I6 -> 171.55484 | V6: 450 - 1000 DT (majoration urgence + saison) | W6: SM-Devis.tn 2025 (estimation cohérente)
A7: Maroc | B7: CLI043 | C7: =IFERROR(VLOOKUP($B7,Types_Pannes_Installations!A:H,4,FALSE()),"?") -> Installation climatiseur split mural 12000 BTU | D7: Standard | E7: Simple | F7: Saison intermédiaire | G7: =IFERROR(VLOOKUP($B7,Types_Pannes_Installations!A:H,6,FALSE()),0) -> 14 | H7: =IFERROR(VLOOKUP($B7,Types_Pannes_Installations!A:H,7,FALSE()),0) -> 2.49 | I7: =IFERROR(VLOOKUP($A7,Donnees_Regionales_MENA!A:H,4,FALSE()),1) -> 9.95 | J7: =IFERROR(VLOOKUP($A7,Donnees_Regionales_MENA!A:H,5,FALSE()),0) -> 110 | K7: =IFERROR(VLOOKUP($A7,Donnees_Regionales_MENA!A:H,6,FALSE()),1) -> 1.05 | L7: =IFERROR(VLOOKUP($D7,Multiplicateurs_Urgence!A:D,4,FALSE()),1) -> 1 | M7: =IFERROR(VLOOKUP($E7,Multiplicateurs_Complexite!A:C,3,FALSE()),1) -> 1 | N7: =IFERROR(VLOOKUP($F7,Multiplicateurs_Saisonnier!A:D,4,FALSE()),1) -> 1 | O7: =IFERROR(VLOOKUP(VLOOKUP($B7,Types_Pannes_Installations!A:H,5,FALSE()),Marge_Fixe!A:C,2,FALSE()),0) -> 6 | P7: =$G7*$I7 -> 139.3 | Q7: =$H7*$J7*$K7*$L7*$M7*$N7 -> 287.595 | R7: =$O7*$I7 -> 59.7 | S7: =$P7+$Q7+$R7 -> 486.595 | T7: =IFERROR(VLOOKUP($A7,Donnees_Regionales_MENA!A:H,2,FALSE()),"") -> Dirham marocain | U7: =$S7/$I7 -> 48.90402 | V7: 500 - 1500 MAD (pose split, hors appareil) | W7: ComptoirElectro.ma / Mano.ma 2025-26
A8: Maroc | B8: MNT164 | C8: =IFERROR(VLOOKUP($B8,Types_Pannes_Installations!A:H,4,FALSE()),"?") -> Entretien annuel chaudière gaz (obligatoire) | D8: Standard | E8: Simple | F8: Saison intermédiaire | G8: =IFERROR(VLOOKUP($B8,Types_Pannes_Installations!A:H,6,FALSE()),0) -> 32 | H8: =IFERROR(VLOOKUP($B8,Types_Pannes_Installations!A:H,7,FALSE()),0) -> 1.2 | I8: =IFERROR(VLOOKUP($A8,Donnees_Regionales_MENA!A:H,4,FALSE()),1) -> 9.95 | J8: =IFERROR(VLOOKUP($A8,Donnees_Regionales_MENA!A:H,5,FALSE()),0) -> 110 | K8: =IFERROR(VLOOKUP($A8,Donnees_Regionales_MENA!A:H,6,FALSE()),1) -> 1.05 | L8: =IFERROR(VLOOKUP($D8,Multiplicateurs_Urgence!A:D,4,FALSE()),1) -> 1 | M8: =IFERROR(VLOOKUP($E8,Multiplicateurs_Complexite!A:C,3,FALSE()),1) -> 1 | N8: =IFERROR(VLOOKUP($F8,Multiplicateurs_Saisonnier!A:D,4,FALSE()),1) -> 1 | O8: =IFERROR(VLOOKUP(VLOOKUP($B8,Types_Pannes_Installations!A:H,5,FALSE()),Marge_Fixe!A:C,2,FALSE()),0) -> 3 | P8: =$G8*$I8 -> 318.4 | Q8: =$H8*$J8*$K8*$L8*$M8*$N8 -> 138.6 | R8: =$O8*$I8 -> 29.85 | S8: =$P8+$Q8+$R8 -> 486.85 | T8: =IFERROR(VLOOKUP($A8,Donnees_Regionales_MENA!A:H,2,FALSE()),"") -> Dirham marocain | U8: =$S8/$I8 -> 48.929648 | V8: 450 - 800 MAD (entretien annuel chaudière) | W8: Mano.ma 2025-26
A10: Lecture : comparez la colonne S (PRIX_FINAL_local) ou U (équivalent USD) à la colonne V (fourchette de marché réelle trouvée en ligne). Si le résultat tombe dans la fourchette ou proche, la calibration est jugée correcte.
